torchfusion_utils/__init__.py
torchfusion_utils/fp16/__init__.py
torchfusion_utils/fp16/fp16.py
torchfusion_utils/initializers/__init__.py
torchfusion_utils/initializers/initializers.py
torchfusion_utils/metrics/__init__.py
torchfusion_utils/metrics/metrics.py
torchfusion_utils/models/__init__.py
torchfusion_utils/models/models.py
torchfusion_utils-0.1.5.dist-info/LICENSE
torchfusion_utils-0.1.5.dist-info/METADATA
torchfusion_utils-0.1.5.dist-info/WHEEL
torchfusion_utils-0.1.5.dist-info/top_level.txt
torchfusion_utils-0.1.5.dist-info/RECORD
